<?xml version="1.0" encoding="utf-8"?>
<products>
  <product name="Cefadroxil" price="1302.20" buyer=" Fox" />
  <product name="PAMO Kill Natural" price="1181.06" buyer="Billy Parker" />
  <product name="Aspen" price="1046.46" buyer="Patricia Cooper" />
  <product name="Fair Foundation SPF 15" price="1394.24" buyer="Benjamin Henry" />
  <product name="Ibuprofen" price="1088.04" buyer="Emily Parker" />
  <product name="PREMIER VALUE ALLERGY" price="1127.61" buyer="Betty Lawson" />
  <product name="Labetalol Hydrochloride" price="1345.11" buyer="Patricia Cooper" />
  <product name="Prednisone" price="1285.99" buyer=" Moreno" />
  <product name="Growing Pains" price="1077.37" buyer="Clarence Fowler" />
  <product name="Americaine" price="1165.75" buyer="Jennifer Riley" />
  <product name="SUMATRIPTAN SUCCINATE" price="1265.94" buyer="Billy Parker" />
  <product name="GEMCITABINE" price="1468.11" buyer="Gary Stevens" />
  <product name="Nighttime Sleep Aid" price="1217.11" buyer="Arthur Reynolds" />
  <product name="Archangelica Eucalyptus" price="1334.91" buyer=" Lawson" />
  <product name="Effervescent Cold Relief" price="1436.07" buyer="Christine Gomez" />
  <product name="Pollens - Trees, Birch Mix" price="1153.54" buyer="Diana Harvey" />
  <product name="IOPE RETIGEN MOISTURE TWIN CAKE NO.21" price="1257.71" buyer="Gloria Alexander" />
</products>